biodumpy/__init__.py
biodumpy/biodumpy.py
biodumpy/data/.DS_Store
biodumpy/data/citations.json
biodumpy/input.py
biodumpy/inputs/BOLD.py
biodumpy/inputs/COL.py
biodumpy/inputs/Crossref.py
biodumpy/inputs/GBIF.py
biodumpy/inputs/INaturalist.py
biodumpy/inputs/IUCN.py
biodumpy/inputs/NCBI.py
biodumpy/inputs/OBIS.py
biodumpy/inputs/WORMS.py
biodumpy/inputs/ZooBank.py
biodumpy/inputs/__init__.py
biodumpy/utils.py
biodumpy-0.1.9.dist-info/METADATA
biodumpy-0.1.9.dist-info/WHEEL
biodumpy-0.1.9.dist-info/licenses/LICENSE
biodumpy-0.1.9.dist-info/RECORD
