Metadata-Version: 2.4
Name: biodumpy
Version: 0.1.9
Summary: A Comprehensive Biological Data Downloader.
License-Expression: GPL-3.0-or-later
License-File: LICENSE
Author: Tomas Golomb
Author-email: tomas.golomb@uib.cat
Requires-Python: >=3.10
Classifier: Programming Language :: Python :: 3
Classifier: Programming Language :: Python :: 3.10
Classifier: Programming Language :: Python :: 3.11
Classifier: Programming Language :: Python :: 3.12
Classifier: Programming Language :: Python :: 3.13
Classifier: Programming Language :: Python :: 3.14
Requires-Dist: beautifulsoup4 (>=4.12.3,<5.0)
Requires-Dist: biopython (>=1.84,<2.0)
Requires-Dist: requests (>=2.32.4,<3.0)
Requires-Dist: tqdm (>=4.66.4,<5.0)
